pypathadd/__init__.py
pypathadd/pypathadd.py
pypathadd-0.1.0.dist-info/LICENSE
pypathadd-0.1.0.dist-info/METADATA
pypathadd-0.1.0.dist-info/WHEEL
pypathadd-0.1.0.dist-info/top_level.txt
pypathadd-0.1.0.dist-info/RECORD
