Metadata-Version: 2.1
Name: pypathadd
Version: 0.1.0
Summary: A function to append all folders and subfolders of the root directory to the Python path.
Home-page: https://github.com/AIGR-sw/pypathadd
Author: Simon Walser
License: MIT License
Project-URL: Homepage, https://github.com/AIGR-sw/pypathadd
Project-URL: Source, https://github.com/AIGR-sw/pypathadd
Project-URL: Tracker, https://github.com/AIGR-sw/pypathadd/issues
Classifier: Programming Language :: Python :: 3
Classifier: License :: OSI Approved :: MIT License
Classifier: Operating System :: OS Independent
Requires-Python: >=3.8
License-File: LICENSE
